{
  "metadata": {
    "name": "no_death_end_challenge_block_break_goal_1_beacon",
    "whenCreated": "2024-06-23T14:17:48.131Z",
    "lastModified": "2024-06-23T14:17:48.131Z",
    "createdBy": "Wiki",
    "builderVersion": "0.0.1",
    "builderMCVersion": "1.20.4",
    "pluginVersion": "0.0.1",
    "pluginMCVersion": "1.20.4"
  },
  "rules": {
    "enabledRules": {
      "noDeath": {
        "punishments": {
          "endPunishment": {
            "affects": "all"
          }
        }
      }
    }
  },
  "goals": {
    "blockBreakGoal": {
      "broken": [
        {
          "collectableName": "beacon",
          "collectableData": {
            "amountNeeded": 1
          }
        }
      ],
      "fixedOrder": true
    }
  },
  "settings": {}
}